{
  "project_info": {
    "project_number": "347926203819",
    "project_id": "sports-event-app-589dc",
    "storage_bucket": "sports-event-app-589dc.firebasestorage.app"
  },
  "client": [
    {
      "client_info": {
        "mobilesdk_app_id": "1:347926203819:android:8b57bbee483d334efcd6ee",
        "android_client_info": {
          "package_name": "com.example.sports_event_app"
        }
      },
      "oauth_client": [],
      "api_key": [
        {
          "current_key": "AIzaSyCGxf66Gif2fJaH0CMJcmnelCCROJvA9jo"
        }
      ],
      "services": {
        "appinvite_service": {
          "other_platform_oauth_client": []
        }
      }
    }
  ],
  "configuration_version": "1"
}